scramjet/__init__.py
scramjet/ansi_color_codes.py
scramjet/pyfca.py
scramjet/streams.py
scramjet/utils.py
scramjet_framework_python-0.2.dist-info/LICENSE
scramjet_framework_python-0.2.dist-info/METADATA
scramjet_framework_python-0.2.dist-info/WHEEL
scramjet_framework_python-0.2.dist-info/top_level.txt
scramjet_framework_python-0.2.dist-info/RECORD
