Metadata-Version: 2.1
Name: scramjet-framework-python
Version: 0.2
Summary: Scramjet is a simple reactive stream programming framework.
Author: Scramjet.org
Author-email: <info@scramjet.org>
Keywords: python,streams
License-File: LICENSE
